ss_python/__init__.py
ss_python/cli.py
ss_python/py.typed
ss_python/settings.py
ss_python-0.0.67.dist-info/licenses/LICENSE
ss_python-0.0.67.dist-info/METADATA
ss_python-0.0.67.dist-info/WHEEL
ss_python-0.0.67.dist-info/entry_points.txt
ss_python-0.0.67.dist-info/top_level.txt
ss_python-0.0.67.dist-info/RECORD
