Metadata-Version: 2.4
Name: ss-python
Version: 0.0.67
Summary: A Python Project Template for Long-Term Maintainability.
Author-email: huxuan <i@huxuan.org>
License: MIT
Project-URL: documentation, https://serious-scaffold.github.io/ss-python
Project-URL: issue, https://github.com/serious-scaffold/ss-python/issues
Project-URL: repository, https://github.com/serious-scaffold/ss-python
Keywords: copier-template,long-term-maintainability,project-template,serious-scaffold
Classifier: Development Status :: 3 - Alpha
Classifier: License :: OSI Approved :: MIT License
Classifier: Operating System :: MacOS :: MacOS X
Classifier: Operating System :: Microsoft :: Windows
Classifier: Operating System :: POSIX :: Linux
Classifier: Programming Language :: Python :: 3 :: Only
Classifier: Programming Language :: Python :: 3.9
Classifier: Programming Language :: Python :: 3.10
Classifier: Programming Language :: Python :: 3.11
Classifier: Programming Language :: Python :: 3.12
Classifier: Programming Language :: Python :: 3.13
Requires-Python: >=3.9
License-File: LICENSE
Requires-Dist: click>=8.1.8
Requires-Dist: pydantic-settings>=2.7.1
Dynamic: license-file
